{
  "_fv": 28,
  "_type": "tool",
  "definition": {
    "renderType": 0,
    "texture": "obsidian_shovel",
    "customModelName": "Normal",
    "name": "Obsidian Shovel",
    "specialInfo": [],
    "creativeTab": {
      "value": "TOOLS"
    },
    "toolType": "Spade",
    "harvestLevel": 8,
    "efficiency": 14.0,
    "attackSpeed": 1.0,
    "enchantability": 55,
    "damageVsEntity": 8.0,
    "usageCount": 1680,
    "blocksAffected": [],
    "hasGlow": false,
    "repairItems": [
      {
        "value": "Blocks.OBSIDIAN"
      }
    ],
    "immuneToFire": false,
    "stayInGridWhenCrafting": false,
    "damageOnCrafting": false
  }
}